st_bordercontainer/__init__.py
st_bordercontainer/frontend/index.html
st_bordercontainer/frontend/main.js
st_bordercontainer/frontend/streamlit-component-lib.js
st_bordercontainer/frontend/style.css
streamlit_bordercontainer-0.0.8.dist-info/LICENSE
streamlit_bordercontainer-0.0.8.dist-info/METADATA
streamlit_bordercontainer-0.0.8.dist-info/WHEEL
streamlit_bordercontainer-0.0.8.dist-info/top_level.txt
streamlit_bordercontainer-0.0.8.dist-info/RECORD
