Metadata-Version: 2.1
Name: streamlit-bordercontainer
Version: 0.0.8
Summary: a box which can set style easily
Author: wuhui
Author-email: 18896724614@139.com
Requires-Python: >=3.7
License-File: LICENSE
Requires-Dist: streamlit >=1.2
Requires-Dist: jinja2
